XLibrary/__init__.py
XLibrary/main.py
XLibrary/submodule1/__init__.py
XLibrary/submodule1/module1.py
XLibrary/submodule1/module2.py
XLibrary/submodule2/__init__.py
XLibrary/submodule2/module1.py
XLibrary/submodule2/module2.py
XLibrary/submodule2/module3.py
XLibrary/submodule2/module4.py
XLibrary/submodule2/module5.py
robotframework_xlibrary-12.1.1.dist-info/LICENSE
robotframework_xlibrary-12.1.1.dist-info/METADATA
robotframework_xlibrary-12.1.1.dist-info/WHEEL
robotframework_xlibrary-12.1.1.dist-info/top_level.txt
robotframework_xlibrary-12.1.1.dist-info/RECORD
