Metadata-Version: 2.1
Name: robotframework-xlibrary
Version: 12.1.1
Summary: Library Custom For Automate
Home-page: https://github.com/Khrx1999/robotframework-xlibrary.git
Author: Tassana Khrueawan
Author-email: tassana.khr@gmail.com
License: UNKNOWN
Platform: UNKNOWN
Classifier: Programming Language :: Python :: 3
Classifier: License :: OSI Approved :: MIT License
Classifier: Operating System :: OS Independent
Classifier: Development Status :: 4 - Beta
Classifier: Intended Audience :: Developers
Classifier: Topic :: Software Development :: Testing
Classifier: Framework :: Robot Framework
Requires-Python: >=3.6
Requires-Dist: robotframework >=6.1.1
Requires-Dist: robotframework-appiumlibrary >=2.0.0
Requires-Dist: robotframework-requests >=0.9.7
Requires-Dist: robotframework-seleniumlibrary >=6.3.0
Requires-Dist: robotframework-mongodb-library >=3.2
Requires-Dist: robotframework-jsonlibrary >=0.5
Requires-Dist: robotframework-jsonvalidator >=2.0.0
Requires-Dist: robotframework-ride >=1.7.4.2
Requires-Dist: robotframework-xlibrary >=12.0.3
Requires-Dist: robotframework-appiumflutterlibrary >=1.0.0
Requires-Dist: rf-googlesheetslibrary >=0.2
Requires-Dist: selenium >=4.11.2
Requires-Dist: requests >=2.31.0
Requires-Dist: bson >=0.5.10
Requires-Dist: pymongo >=4.7.2
Requires-Dist: pandas >=1.3.5
Requires-Dist: openpyxl >=3.1.3
Requires-Dist: beautifulsoup4 >=4.12.3
Requires-Dist: requests-oauthlib >=2.0.0
Requires-Dist: pytest >=7.4.4
Requires-Dist: opencv-python >=4.10.0.84
Requires-Dist: numpy >=1.21.6
Requires-Dist: Pillow >=9.5.0
Requires-Dist: google-api-python-client >=2.132.0
Requires-Dist: google-auth >=2.29.0
Requires-Dist: google-auth-oauthlib >=1.2.0
Requires-Dist: google-auth-httplib2 >=0.2.0
Requires-Dist: httplib2 >=0.22.0
Requires-Dist: jsonpath-ng >=1.6.1
Requires-Dist: jsonpath-rw >=1.4.0
Requires-Dist: jsonpath-rw-ext >=1.2.2
Requires-Dist: oauthlib >=3.2.2
Requires-Dist: dnspython >=2.3.0
Requires-Dist: tqdm >=4.66.4
